{
  "generator-jhipster": {
    "applicationIndex": 0,
    "applicationType": "monolith",
    "authenticationType": "jwt",
    "baseName": "ecommerce",
    "buildTool": "maven",
    "cacheProvider": "no",
    "clientFramework": "vue",
    "clientTheme": "none",
    "creationTimestamp": 1688359016713,
    "databaseType": "sql",
    "devDatabaseType": "h2Disk",
    "devServerPort": 9060,
    "dtoSuffix": "DTO",
    "enableGradleEnterprise": null,
    "enableHibernateCache": false,
    "enableSwaggerCodegen": false,
    "enableTranslation": false,
    "entities": ["Brand", "Product", "Price"],
    "entitySuffix": "",
    "gradleEnterpriseHost": null,
    "jhiPrefix": "jhi",
    "jhipsterVersion": "8.0.0-beta.1",
    "jwtSecretKey": "M2JmYzg3N2YwZWU3N2JkMzliMzBjODFjMGFhODRhY2IyODEyYmEwMTUzNGVkODY0YTUyZmExZTUxNGM3NzBiOGM0YmQ5ZGM4ODlhYjAwYzFlYjY3MTQ1NjA3ZmRmNmY2ODY0YmNmN2JlNmE0ZmVjMzBmNzY2NTQ1YTE5MWNkN2Q=",
    "lastLiquibaseTimestamp": 1688445835000,
    "messageBroker": false,
    "microfrontend": false,
    "microfrontends": [],
    "nativeLanguage": "es",
    "packageFolder": "com/decskill",
    "packageName": "com.decskill",
    "pages": [],
    "prodDatabaseType": "postgresql",
    "reactive": false,
    "searchEngine": false,
    "serverPort": null,
    "serverSideOptions": [],
    "serviceDiscoveryType": false,
    "skipCheckLengthOfIdentifier": false,
    "skipClient": false,
    "skipFakeData": false,
    "skipUserManagement": false,
    "testFrameworks": [],
    "websocket": false,
    "withAdminUi": true
  }
}
